{
  "generated_at": "Friday, April 24 2026  09:04 PT",
  "market_status": "Live \u2014 as of 12:04 ET",
  "stocks": {
    "S&P 500": {
      "price": 7161.42,
      "change_pct": 0.75
    },
    "Nasdaq": {
      "price": 24794.78,
      "change_pct": 1.46
    },
    "Dow Jones": {
      "price": 49237.41,
      "change_pct": -0.14
    },
    "Russell 2000": {
      "price": 2794.26,
      "change_pct": 0.69
    }
  },
  "commodities": {
    "Gold": {
      "price": 4745.0,
      "change_pct": 1.23
    },
    "Oil (WTI)": {
      "price": 93.27,
      "change_pct": -3.47
    },
    "Silver": {
      "price": 76.4,
      "change_pct": 2.13
    }
  },
  "crypto": {
    "BTC": {
      "price": 77987,
      "change_pct": -0.56
    },
    "ETH": {
      "price": 2322.08,
      "change_pct": -0.46
    },
    "SOL": {
      "price": 86.45,
      "change_pct": 0.12
    },
    "BNB": {
      "price": 639.95,
      "change_pct": -0.04
    }
  },
  "headlines": [
    {
      "source": "CNBC",
      "title": "DOJ drops criminal probe of Fed Chair Powell, removes hurdle for Warsh confirmation"
    },
    {
      "source": "CNBC",
      "title": "Iran's top diplomat expected in Pakistan on Friday night to discuss peace plans: MS NOW"
    },
    {
      "source": "MarketWatch",
      "title": "\u2018My child requires lifelong support\u2019: I\u2019m in my 40s with $330,000 for retirement. How can I make this last both our lifetimes?"
    },
    {
      "source": "MarketWatch",
      "title": "Trump\u2019s Justice Department drops its probe into Fed\u2019s Powell, paving the way for Warsh\u2019s confirmation"
    }
  ]
}