{
  "generated_at": "Friday, June 05 2026  13:24 PT",
  "market_status": "Prior close \u2014 market closed",
  "stocks": {
    "S&P 500": {
      "price": 7383.74,
      "change_pct": -2.64
    },
    "Nasdaq": {
      "price": 25709.43,
      "change_pct": -4.18
    },
    "Dow Jones": {
      "price": 50866.78,
      "change_pct": -1.35
    },
    "Russell 2000": {
      "price": 2833.5,
      "change_pct": -3.47
    }
  },
  "commodities": {
    "Gold": {
      "price": 4341.1,
      "change_pct": -2.85
    },
    "Oil (WTI)": {
      "price": 90.36,
      "change_pct": -2.98
    },
    "Silver": {
      "price": 67.79,
      "change_pct": -7.0
    }
  },
  "crypto": {
    "BTC": {
      "price": 60852,
      "change_pct": -3.8
    },
    "ETH": {
      "price": 1594.31,
      "change_pct": -9.92
    },
    "SOL": {
      "price": 64.01,
      "change_pct": -7.05
    },
    "BNB": {
      "price": 572.31,
      "change_pct": -5.29
    }
  },
  "headlines": [
    {
      "source": "CNBC",
      "title": "Nasdaq falls 4% and suffers worst day since April 2025 as traders flee chip stocks: Live updates"
    },
    {
      "source": "CNBC",
      "title": "Meta's stock sinks on report company could raise tens of billions of dollars to fund AI push"
    },
    {
      "source": "MarketWatch",
      "title": "For the first time ever, an S&P 500 ETF has over $1 trillion in assets. Here\u2019s why that should worry you."
    },
    {
      "source": "MarketWatch",
      "title": "This hot new financial product has Wall Street spooked. What you should know before trying it out."
    }
  ]
}