{
  "generated_at": "Thursday, April 30 2026  10:49 PT",
  "market_status": "Live \u2014 as of 13:49 ET",
  "stocks": {
    "S&P 500": {
      "price": 7190.35,
      "change_pct": 0.74
    },
    "Nasdaq": {
      "price": 24821.94,
      "change_pct": 0.6
    },
    "Dow Jones": {
      "price": 49605.01,
      "change_pct": 1.51
    },
    "Russell 2000": {
      "price": 2787.28,
      "change_pct": 1.74
    }
  },
  "commodities": {
    "Gold": {
      "price": 4629.4,
      "change_pct": 1.35
    },
    "Oil (WTI)": {
      "price": 104.04,
      "change_pct": -4.61
    },
    "Silver": {
      "price": 74.01,
      "change_pct": 2.14
    }
  },
  "crypto": {
    "BTC": {
      "price": 76169,
      "change_pct": 0.24
    },
    "ETH": {
      "price": 2255.44,
      "change_pct": -0.83
    },
    "SOL": {
      "price": 82.98,
      "change_pct": -0.02
    },
    "BNB": {
      "price": 616.15,
      "change_pct": -0.52
    }
  },
  "headlines": [
    {
      "source": "CNBC",
      "title": "Google cloud growth tops Microsoft and Amazon as all three beat estimates on AI demand"
    },
    {
      "source": "CNBC",
      "title": "DHS shutdown set to end after House passes bill to fund most of agency, including TSA"
    },
    {
      "source": "MarketWatch",
      "title": "Target-date funds are \u2018a flawed tool.\u2019 Here\u2019s how you can do better."
    },
    {
      "source": "MarketWatch",
      "title": "Americans are embracing this terrible car-buying habit. It\u2019s costing them thousands of dollars."
    }
  ]
}