{
  "generated_at": "Wednesday, May 06 2026  23:09 PT",
  "market_status": "Prior close \u2014 market closed",
  "stocks": {
    "S&P 500": {
      "price": 7365.12,
      "change_pct": 1.46
    },
    "Nasdaq": {
      "price": 25838.94,
      "change_pct": 2.02
    },
    "Dow Jones": {
      "price": 49910.59,
      "change_pct": 1.24
    },
    "Russell 2000": {
      "price": 2886.77,
      "change_pct": 1.47
    }
  },
  "commodities": {
    "Gold": {
      "price": 4711.3,
      "change_pct": 0.05
    },
    "Oil (WTI)": {
      "price": 95.34,
      "change_pct": -0.45
    },
    "Silver": {
      "price": 78.24,
      "change_pct": 0.1
    }
  },
  "crypto": {
    "BTC": {
      "price": 81034,
      "change_pct": -0.31
    },
    "ETH": {
      "price": 2329.21,
      "change_pct": -1.41
    },
    "SOL": {
      "price": 88.62,
      "change_pct": 1.4
    },
    "BNB": {
      "price": 646.67,
      "change_pct": 1.87
    }
  },
  "headlines": [
    {
      "source": "CNBC",
      "title": "Iran war threatens jet fuel shortage that could disrupt summer travel in Asia and Europe"
    },
    {
      "source": "CNBC",
      "title": "Snap issues cautious guidance as Perplexity deal ends, Middle East 'geopolitical situation' causes uncertainty"
    },
    {
      "source": "MarketWatch",
      "title": "Hantavirus outbreaks rarely happen. This Andes strain is \u2018a complicated public-health situation.\u2019"
    },
    {
      "source": "MarketWatch",
      "title": "Arm puts a big number on its newest venture, but its stock falls"
    }
  ]
}