{
  "generated_at": "Tuesday, July 07 2026  22:49 PT",
  "market_status": "Prior close \u2014 market closed",
  "stocks": {
    "S&P 500": {
      "price": 7503.85,
      "change_pct": -0.45
    },
    "Nasdaq": {
      "price": 25818.69,
      "change_pct": -1.16
    },
    "Dow Jones": {
      "price": 52925.15,
      "change_pct": -0.25
    },
    "Russell 2000": {
      "price": 2982.49,
      "change_pct": -0.9
    }
  },
  "commodities": {
    "Gold": {
      "price": 4138.7,
      "change_pct": -0.02
    },
    "Oil (WTI)": {
      "price": 72.63,
      "change_pct": 0.53
    },
    "Silver": {
      "price": 61.29,
      "change_pct": 0.38
    }
  },
  "crypto": {
    "BTC": {
      "price": 62538,
      "change_pct": -0.91
    },
    "ETH": {
      "price": 1750.21,
      "change_pct": -1.0
    },
    "SOL": {
      "price": 78.38,
      "change_pct": -3.16
    },
    "BNB": {
      "price": 567.42,
      "change_pct": -1.94
    }
  },
  "headlines": [
    {
      "source": "CNBC",
      "title": "Oil jumps as U.S. 'powerful strikes' against Iran risk unraveling fragile Mideast truce"
    },
    {
      "source": "CNBC",
      "title": "Lawmakers probe growing use of Chinese AI models in U.S. companies"
    },
    {
      "source": "MarketWatch",
      "title": "Plot twist: Gen Z is buying houses after all. Here\u2019s how they\u2019re doing it."
    },
    {
      "source": "MarketWatch",
      "title": "Rivian\u2019s stock sale triggers worst rout for the shares in nearly two years"
    }
  ]
}