{
  "generated_at": "Tuesday, March 17 2026  22:22 PT",
  "market_status": "Prior close \u2014 market closed",
  "stocks": {
    "S&P 500": {
      "price": 6716.09,
      "change_pct": 0.25
    },
    "Nasdaq": {
      "price": 22479.53,
      "change_pct": 0.47
    },
    "Dow Jones": {
      "price": 46993.26,
      "change_pct": 0.1
    },
    "Russell 2000": {
      "price": 2519.99,
      "change_pct": 0.67
    }
  },
  "commodities": {
    "Gold": {
      "price": 4994.8,
      "change_pct": -0.07
    },
    "Oil (WTI)": {
      "price": 92.58,
      "change_pct": -1.29
    },
    "Silver": {
      "price": 79.31,
      "change_pct": 0.53
    }
  },
  "crypto": {
    "BTC": {
      "price": 74235,
      "change_pct": -0.07
    },
    "ETH": {
      "price": 2329.11,
      "change_pct": 0.68
    },
    "SOL": {
      "price": 94.32,
      "change_pct": 0.44
    },
    "BNB": {
      "price": 673.22,
      "change_pct": -0.42
    }
  },
  "headlines": [
    {
      "source": "CNBC",
      "title": "Iran launches retaliatory strikes on Israel and U.S. assets after security chief Larijani is killed"
    },
    {
      "source": "CNBC",
      "title": "The Fed issues its latest interest rate decision Wednesday. Here's what to expect"
    },
    {
      "source": "MarketWatch",
      "title": "The \u2018smart money\u2019 on Wall Street hates these bonds \u2014 but they may be a golden buying opportunity for you"
    },
    {
      "source": "MarketWatch",
      "title": "The spike in gas prices might affect Olive Garden sales, but not in the way you\u2019d expect"
    }
  ]
}