{
  "generated_at": "Thursday, July 09 2026  15:49 PT",
  "market_status": "Prior close \u2014 market closed",
  "stocks": {
    "S&P 500": {
      "price": 7543.64,
      "change_pct": 0.81
    },
    "Nasdaq": {
      "price": 26206.89,
      "change_pct": 1.3
    },
    "Dow Jones": {
      "price": 52487.41,
      "change_pct": 0.27
    },
    "Russell 2000": {
      "price": 2992.54,
      "change_pct": 1.22
    }
  },
  "commodities": {
    "Gold": {
      "price": 4133.3,
      "change_pct": 1.5
    },
    "Oil (WTI)": {
      "price": 71.82,
      "change_pct": -3.31
    },
    "Silver": {
      "price": 60.34,
      "change_pct": 3.61
    }
  },
  "crypto": {
    "BTC": {
      "price": 63308,
      "change_pct": 1.7
    },
    "ETH": {
      "price": 1748.81,
      "change_pct": 0.58
    },
    "SOL": {
      "price": 78.18,
      "change_pct": 1.05
    },
    "BNB": {
      "price": 570.37,
      "change_pct": 0.57
    }
  },
  "headlines": [
    {
      "source": "CNBC",
      "title": "Inside NATO's extraordinary 48 hours that revealed Trump's grip on global diplomacy"
    },
    {
      "source": "CNBC",
      "title": "Kevin Warsh names members of his Federal Reserve task forces, including Marc Andreessen, Doug McMillon"
    },
    {
      "source": "MarketWatch",
      "title": "Taco Bell is reportedly pulling produce from some stores. Here\u2019s what to know."
    },
    {
      "source": "MarketWatch",
      "title": "Why a hidden divergence between the VIX and Nasdaq volatility has the smart money on edge"
    }
  ]
}