{
  "generated_at": "Thursday, July 16 2026  13:55 PT",
  "market_status": "Prior close \u2014 market closed",
  "stocks": {
    "S&P 500": {
      "price": 7533.77,
      "change_pct": -0.51
    },
    "Nasdaq": {
      "price": 25881.95,
      "change_pct": -1.47
    },
    "Dow Jones": {
      "price": 52552.97,
      "change_pct": -0.2
    },
    "Russell 2000": {
      "price": 2974.57,
      "change_pct": -0.06
    }
  },
  "commodities": {
    "Gold": {
      "price": 3979.0,
      "change_pct": -1.53
    },
    "Oil (WTI)": {
      "price": 78.78,
      "change_pct": -0.98
    },
    "Silver": {
      "price": 55.77,
      "change_pct": -3.04
    }
  },
  "crypto": {
    "BTC": {
      "price": 64078,
      "change_pct": -1.32
    },
    "ETH": {
      "price": 1871.68,
      "change_pct": -2.66
    },
    "SOL": {
      "price": 75.73,
      "change_pct": -2.15
    },
    "BNB": {
      "price": 574.51,
      "change_pct": -1.03
    }
  },
  "headlines": [
    {
      "source": "CNBC",
      "title": "Netflix reports earnings in line with expectations, says company will give fewer engagement updates"
    },
    {
      "source": "CNBC",
      "title": "Here's why the housing market is hurting so much this summer"
    },
    {
      "source": "MarketWatch",
      "title": "Netflix is getting stingier about its viewing data, and Wall Street isn\u2019t happy"
    },
    {
      "source": "MarketWatch",
      "title": "As SpaceX\u2019s stock notches first close below IPO price, the company is gearing up for a crucial launch"
    }
  ]
}