{
  "generated_at": "Sunday, June 14 2026  16:45 PT",
  "market_status": "Friday close \u2014 market closed",
  "stocks": {
    "S&P 500": {
      "price": 7431.46,
      "change_pct": 0.5
    },
    "Nasdaq": {
      "price": 25888.84,
      "change_pct": 0.31
    },
    "Dow Jones": {
      "price": 51202.26,
      "change_pct": 0.7
    },
    "Russell 2000": {
      "price": 2943.99,
      "change_pct": 0.79
    }
  },
  "commodities": {
    "Gold": {
      "price": 4305.0,
      "change_pct": 1.56
    },
    "Oil (WTI)": {
      "price": 81.11,
      "change_pct": -4.44
    },
    "Silver": {
      "price": 70.04,
      "change_pct": 3.05
    }
  },
  "crypto": {
    "BTC": {
      "price": 65550,
      "change_pct": 1.8
    },
    "ETH": {
      "price": 1719.13,
      "change_pct": 2.43
    },
    "SOL": {
      "price": 70.71,
      "change_pct": 2.57
    },
    "BNB": {
      "price": 615.25,
      "change_pct": 0.99
    }
  },
  "headlines": [
    {
      "source": "CNBC",
      "title": "U.S. and Iran agree on peace deal to end the war, Trump and Pakistan say"
    },
    {
      "source": "CNBC",
      "title": "Stock futures jump after the U.S. and Iran reach a deal to end the war: Live updates"
    },
    {
      "source": "MarketWatch",
      "title": "Stock futures jump, oil prices fall as Trump says U.S. has reached peace deal with Iran"
    },
    {
      "source": "MarketWatch",
      "title": "Will the real Kevin Warsh please stand up? Ahead of his first Fed meeting, economists honestly don\u2019t know what to expect."
    }
  ]
}